achn/__init__.py
achn/_modidx.py
achn/core.py
achn-0.0.6.dist-info/LICENSE
achn-0.0.6.dist-info/METADATA
achn-0.0.6.dist-info/WHEEL
achn-0.0.6.dist-info/entry_points.txt
achn-0.0.6.dist-info/top_level.txt
achn-0.0.6.dist-info/RECORD
